Workbook

Sheet Start Here
A1: Cleaning Business Job Profit & Quote Calculator
A2: Start here
A4: What this does | B4: Tells you what to charge so a job actually makes the profit you want, then shows whether the job did.
A5: Step 1 | B5: Go to the Settings sheet. Enter your labor cost per hour, overhead %, target margin, mileage cost, recurring discount and minimum price.
A6: Step 2 | B6: Go to the Quote sheet. Describe the job in the yellow cells. Quote the price in 'QUOTE THIS PRICE'.
A7: Step 3 | B7: See the Examples sheet for three fictional jobs (a recurring home, a move-out deep clean, a small office).
A8: Step 4 | B8: After each job, add a row on the Job Tracker with your ACTUAL hours, supplies and miles. Check the Dashboard to see which jobs lost money.
A9: Step 5 | B9: Use the Client Tracker for leads and recurring clients, the Follow-Up Templates for messages, and the 12-Month Tracker to compare profit with your goal.
A10: Colors | B10: Yellow = you type here. Gray = calculated, don't type over it. Blue = key results.
A11: Margin vs markup | B11: Margin = profit / price. Markup = profit / cost. Example: a job costs $100. A 40% margin means price = 100 / (1 - 0.40) = $166.67, profit $66.67. That is a 66.7% markup but a 40% margin. This sheet uses margin so your profit % is what you really keep.
A12: Google Sheets | B12: Upload this file to Google Drive and open with Google Sheets, or use File > Import. All formulas are standard and work in both.
A13: Not included | B13: No macros. No tax, payroll or accounting features. This workbook is a planning tool. It is not tax, accounting, legal or financial advice. Check your numbers with your own accountant.
A14: Support | B14: This is a template. It can't know your costs. If a result looks wrong, check your Settings first.

Sheet Settings
A1: Settings
A2: Starter values are filled in so the Examples work. REPLACE them with your own numbers.
A3: Setting | B3: Value | C3: What it means
A4: Labor cost per cleaner-hour | B4: 18 | C4: What one cleaner costs you per hour: wages PLUS payroll taxes/workers' comp. Pay yourself too.
A5: Overhead (% added on top of direct cost) | B5: 0.1 | C5: Insurance, software, phone, cleaning equipment wear, admin time. 8-15% is common; use your real number.
A6: Target profit margin | B6: 0.35 | C6: Profit as a % of the PRICE (not of cost). 35% margin means $35 of every $100 you charge is profit.
A7: Vehicle cost per mile | B7: 0.67 | C7: Your real cost to drive one mile (fuel, wear, insurance). Check the current IRS mileage rate as a reference.
A8: Recurring-client discount | B8: 0.1 | C8: Discount off the one-time price for recurring clients. Enter 0% for none.
A9: Minimum job price | B9: 90 | C9: Never quote below this, even for a tiny job.
A11: This workbook is a planning tool. It is not tax, accounting, legal or financial advice. Check your numbers with your own accountant.

Sheet Quote
A1: Job Quote Calculator
A2: Fill the yellow cells. Gray cells calculate. Quote the 'QUOTE THIS PRICE' number.
A3: Client / job name
A4: Job type (One-time or Recurring)
A5: Number of cleaners
A6: Hours on site per cleaner
A7: Supplies & materials for this visit ($)
A8: Round-trip miles (all vehicles)
A9: Other direct costs ($, e.g. equipment rental)
A10: Visits per month (recurring jobs only)
A12: RESULTS
A13: Total labor hours | B13: =B5*B6
A14: Labor cost | B14: =B13*Settings!$B$4
A15: Travel cost | B15: =B8*Settings!$B$7
A16: Direct cost (labor + travel + supplies + other) | B16: =B14+B15+B7+B9
A17: Overhead | B17: =B16*Settings!$B$5
A18: TOTAL COST to do this visit | B18: =B16+B17
A19: Price needed to hit your target margin | B19: =IF(Settings!$B$6>=1,0,B18/(1-Settings!$B$6))
A20: Recurring discount applied | B20: =IF(B4="Recurring",B19*Settings!$B$8,0)
A21: QUOTE THIS PRICE (per visit) | B21: =MAX(Settings!$B$9,ROUNDUP(B19-B20,0)) | C21: Rounded up to the next whole dollar and never below your minimum job price.
A22: Profit per visit | B22: =B21-B18
A23: Profit margin (profit / price) | B23: =IF(B21=0,0,B22/B21) | C23: Margin = profit / PRICE. This is what you keep from every dollar charged.
A24: Markup on cost (profit / cost) | B24: =IF(B18=0,0,B22/B18) | C24: Markup = profit / COST. A 50% markup is only a 33% margin. Don't mix them up.
A25: Profit per labor hour | B25: =IF(B13=0,0,B22/B13) | C25: Profit left after ALL costs, divided by labor hours.
A26: Monthly revenue (recurring) | B26: =IF(B4="Recurring",B21*B10,0)
A27: Monthly profit (recurring) | B27: =IF(B4="Recurring",B22*B10,0)
A28: Check | B28: =IF(Settings!$B$6>=1,"Fix target margin on Settings (must be under 100%)",IF(B13=0,"Enter cleaners and hours to get a result",IF(B22<0,"LOSING MONEY - raise the price",IF(B23<Settings!$B$6-0.0001,"Below target margin because of the recurring discount - fine if intended","OK - at or above target margin"))))
A30: This workbook is a planning tool. It is not tax, accounting, legal or financial advice. Check your numbers with your own accountant.

Sheet Examples
A1: Three example jobs (fictional)
A2: Same math as the Quote sheet, using your Settings. Change Settings to see prices move.
A3: Client / job name | B3: Standard 3BR/2BA - biweekly | C3: Move-out deep clean - 4BR | D3: Small office - nightly, 5x/week
A4: Job type (One-time or Recurring) | B4: Recurring | C4: One-time | D4: Recurring
A5: Number of cleaners | B5: 2 | C5: 3 | D5: 1
A6: Hours on site per cleaner | B6: 2 | C6: 3 | D6: 1.5
A7: Supplies & materials for this visit ($) | B7: 6 | C7: 25 | D7: 5
A8: Round-trip miles (all vehicles) | B8: 14 | C8: 22 | D8: 8
A9: Other direct costs ($, e.g. equipment rental) | B9: 0 | C9: 15 | D9: 0
A10: Visits per month (recurring jobs only) | B10: 2 | D10: 22
A12: RESULTS
A13: Total labor hours | B13: =B5*B6 | C13: =C5*C6 | D13: =D5*D6
A14: Labor cost | B14: =B13*Settings!$B$4 | C14: =C13*Settings!$B$4 | D14: =D13*Settings!$B$4
A15: Travel cost | B15: =B8*Settings!$B$7 | C15: =C8*Settings!$B$7 | D15: =D8*Settings!$B$7
A16: Direct cost (labor + travel + supplies + other) | B16: =B14+B15+B7+B9 | C16: =C14+C15+C7+C9 | D16: =D14+D15+D7+D9
A17: Overhead | B17: =B16*Settings!$B$5 | C17: =C16*Settings!$B$5 | D17: =D16*Settings!$B$5
A18: TOTAL COST to do this visit | B18: =B16+B17 | C18: =C16+C17 | D18: =D16+D17
A19: Price needed to hit your target margin | B19: =IF(Settings!$B$6>=1,0,B18/(1-Settings!$B$6)) | C19: =IF(Settings!$B$6>=1,0,C18/(1-Settings!$B$6)) | D19: =IF(Settings!$B$6>=1,0,D18/(1-Settings!$B$6))
A20: Recurring discount applied | B20: =IF(B4="Recurring",B19*Settings!$B$8,0) | C20: =IF(C4="Recurring",C19*Settings!$B$8,0) | D20: =IF(D4="Recurring",D19*Settings!$B$8,0)
A21: QUOTE THIS PRICE (per visit) | B21: =MAX(Settings!$B$9,ROUNDUP(B19-B20,0)) | C21: =MAX(Settings!$B$9,ROUNDUP(C19-C20,0)) | D21: =MAX(Settings!$B$9,ROUNDUP(D19-D20,0))
A22: Profit per visit | B22: =B21-B18 | C22: =C21-C18 | D22: =D21-D18
A23: Profit margin (profit / price) | B23: =IF(B21=0,0,B22/B21) | C23: =IF(C21=0,0,C22/C21) | D23: =IF(D21=0,0,D22/D21)
A24: Markup on cost (profit / cost) | B24: =IF(B18=0,0,B22/B18) | C24: =IF(C18=0,0,C22/C18) | D24: =IF(D18=0,0,D22/D18)
A25: Profit per labor hour | B25: =IF(B13=0,0,B22/B13) | C25: =IF(C13=0,0,C22/C13) | D25: =IF(D13=0,0,D22/D13)
A26: Monthly revenue (recurring) | B26: =IF(B4="Recurring",B21*B10,0) | C26: =IF(C4="Recurring",C21*C10,0) | D26: =IF(D4="Recurring",D21*D10,0)
A27: Monthly profit (recurring) | B27: =IF(B4="Recurring",B22*B10,0) | C27: =IF(C4="Recurring",C22*C10,0) | D27: =IF(D4="Recurring",D22*D10,0)
A28: Check | B28: =IF(Settings!$B$6>=1,"Fix target margin on Settings (must be under 100%)",IF(B13=0,"Enter cleaners and hours to get a result",IF(B22<0,"LOSING MONEY - raise the price",IF(B23<Settings!$B$6-0.0001,"Below target margin because of the recurring discount - fine if intended","OK - at or above target margin")))) | C28: =IF(Settings!$B$6>=1,"Fix target margin on Settings (must be under 100%)",IF(C13=0,"Enter cleaners and hours to get a result",IF(C22<0,"LOSING MONEY - raise the price",IF(C23<Settings!$B$6-0.0001,"Below target margin because of the recurring discount - fine if intended","OK - at or above target margin")))) | D28: =IF(Settings!$B$6>=1,"Fix target margin on Settings (must be under 100%)",IF(D13=0,"Enter cleaners and hours to get a result",IF(D22<0,"LOSING MONEY - raise the price",IF(D23<Settings!$B$6-0.0001,"Below target margin because of the recurring discount - fine if intended","OK - at or above target margin"))))

Sheet Job Tracker
A1: Job Tracker
A2: One row per completed job. Enter the quote and your ACTUAL numbers. Gray columns calculate.
A4: Date | B4: Client / job | C4: Price charged | D4: Estimated cost (from quote) | E4: Actual labor hours (total) | F4: Actual supplies ($) | G4: Actual miles | H4: Other costs ($) | I4: Actual total cost | J4: Actual profit | K4: Actual margin | L4: Planned profit | M4: Profit vs plan | N4: Check
I5: =IF(C5="","",(E5*Settings!$B$4+F5+G5*Settings!$B$7+H5)*(1+Settings!$B$5)) | J5: =IF(C5="","",C5-I5) | K5: =IF(C5="","",IF(C5=0,0,J5/C5)) | L5: =IF(C5="","",C5-D5) | M5: =IF(C5="","",J5-L5) | N5: =IF(C5="","",IF(J5<0,"LOST MONEY",IF(K5<Settings!$B$6-0.0001,"Below target margin","OK")))
I6: =IF(C6="","",(E6*Settings!$B$4+F6+G6*Settings!$B$7+H6)*(1+Settings!$B$5)) | J6: =IF(C6="","",C6-I6) | K6: =IF(C6="","",IF(C6=0,0,J6/C6)) | L6: =IF(C6="","",C6-D6) | M6: =IF(C6="","",J6-L6) | N6: =IF(C6="","",IF(J6<0,"LOST MONEY",IF(K6<Settings!$B$6-0.0001,"Below target margin","OK")))
I7: =IF(C7="","",(E7*Settings!$B$4+F7+G7*Settings!$B$7+H7)*(1+Settings!$B$5)) | J7: =IF(C7="","",C7-I7) | K7: =IF(C7="","",IF(C7=0,0,J7/C7)) | L7: =IF(C7="","",C7-D7) | M7: =IF(C7="","",J7-L7) | N7: =IF(C7="","",IF(J7<0,"LOST MONEY",IF(K7<Settings!$B$6-0.0001,"Below target margin","OK")))
I8: =IF(C8="","",(E8*Settings!$B$4+F8+G8*Settings!$B$7+H8)*(1+Settings!$B$5)) | J8: =IF(C8="","",C8-I8) | K8: =IF(C8="","",IF(C8=0,0,J8/C8)) | L8: =IF(C8="","",C8-D8) | M8: =IF(C8="","",J8-L8) | N8: =IF(C8="","",IF(J8<0,"LOST MONEY",IF(K8<Settings!$B$6-0.0001,"Below target margin","OK")))
I9: =IF(C9="","",(E9*Settings!$B$4+F9+G9*Settings!$B$7+H9)*(1+Settings!$B$5)) | J9: =IF(C9="","",C9-I9) | K9: =IF(C9="","",IF(C9=0,0,J9/C9)) | L9: =IF(C9="","",C9-D9) | M9: =IF(C9="","",J9-L9) | N9: =IF(C9="","",IF(J9<0,"LOST MONEY",IF(K9<Settings!$B$6-0.0001,"Below target margin","OK")))
I10: =IF(C10="","",(E10*Settings!$B$4+F10+G10*Settings!$B$7+H10)*(1+Settings!$B$5)) | J10: =IF(C10="","",C10-I10) | K10: =IF(C10="","",IF(C10=0,0,J10/C10)) | L10: =IF(C10="","",C10-D10) | M10: =IF(C10="","",J10-L10) | N10: =IF(C10="","",IF(J10<0,"LOST MONEY",IF(K10<Settings!$B$6-0.0001,"Below target margin","OK")))
I11: =IF(C11="","",(E11*Settings!$B$4+F11+G11*Settings!$B$7+H11)*(1+Settings!$B$5)) | J11: =IF(C11="","",C11-I11) | K11: =IF(C11="","",IF(C11=0,0,J11/C11)) | L11: =IF(C11="","",C11-D11) | M11: =IF(C11="","",J11-L11) | N11: =IF(C11="","",IF(J11<0,"LOST MONEY",IF(K11<Settings!$B$6-0.0001,"Below target margin","OK")))
I12: =IF(C12="","",(E12*Settings!$B$4+F12+G12*Settings!$B$7+H12)*(1+Settings!$B$5)) | J12: =IF(C12="","",C12-I12) | K12: =IF(C12="","",IF(C12=0,0,J12/C12)) | L12: =IF(C12="","",C12-D12) | M12: =IF(C12="","",J12-L12) | N12: =IF(C12="","",IF(J12<0,"LOST MONEY",IF(K12<Settings!$B$6-0.0001,"Below target margin","OK")))
I13: =IF(C13="","",(E13*Settings!$B$4+F13+G13*Settings!$B$7+H13)*(1+Settings!$B$5)) | J13: =IF(C13="","",C13-I13) | K13: =IF(C13="","",IF(C13=0,0,J13/C13)) | L13: =IF(C13="","",C13-D13) | M13: =IF(C13="","",J13-L13) | N13: =IF(C13="","",IF(J13<0,"LOST MONEY",IF(K13<Settings!$B$6-0.0001,"Below target margin","OK")))
I14: =IF(C14="","",(E14*Settings!$B$4+F14+G14*Settings!$B$7+H14)*(1+Settings!$B$5)) | J14: =IF(C14="","",C14-I14) | K14: =IF(C14="","",IF(C14=0,0,J14/C14)) | L14: =IF(C14="","",C14-D14) | M14: =IF(C14="","",J14-L14) | N14: =IF(C14="","",IF(J14<0,"LOST MONEY",IF(K14<Settings!$B$6-0.0001,"Below target margin","OK")))
I15: =IF(C15="","",(E15*Settings!$B$4+F15+G15*Settings!$B$7+H15)*(1+Settings!$B$5)) | J15: =IF(C15="","",C15-I15) | K15: =IF(C15="","",IF(C15=0,0,J15/C15)) | L15: =IF(C15="","",C15-D15) | M15: =IF(C15="","",J15-L15) | N15: =IF(C15="","",IF(J15<0,"LOST MONEY",IF(K15<Settings!$B$6-0.0001,"Below target margin","OK")))
I16: =IF(C16="","",(E16*Settings!$B$4+F16+G16*Settings!$B$7+H16)*(1+Settings!$B$5)) | J16: =IF(C16="","",C16-I16) | K16: =IF(C16="","",IF(C16=0,0,J16/C16)) | L16: =IF(C16="","",C16-D16) | M16: =IF(C16="","",J16-L16) | N16: =IF(C16="","",IF(J16<0,"LOST MONEY",IF(K16<Settings!$B$6-0.0001,"Below target margin","OK")))
... I104: =IF(C104="","",(E104*Settings!$B$4+F104+G104*Settings!$B$7+H104)*(1+Settings!$B$5)) | J104: =IF(C104="","",C104-I104) | K104: =IF(C104="","",IF(C104=0,0,J104/C104)) | L104: =IF(C104="","",C104-D104) | M104: =IF(C104="","",J104-L104) | N104: =IF(C104="","",IF(J104<0,"LOST MONEY",IF(K104<Settings!$B$6-0.0001,"Below target margin","OK")))

Sheet Dashboard
A1: Dashboard
A2: Updates automatically from the Job Tracker.
A3: Measure | B3: Value
A4: Jobs tracked | B4: =COUNT('Job Tracker'!$C$5:$C$104)
A5: Total revenue | B5: =SUM('Job Tracker'!$C$5:$C$104)
A6: Total actual cost | B6: =SUM('Job Tracker'!$I$5:$I$104)
A7: Total actual profit | B7: =SUM('Job Tracker'!$J$5:$J$104)
A8: Overall profit margin | B8: =IF(B5=0,0,B7/B5)
A9: Average profit per job | B9: =IF(B4=0,0,B7/B4)
A10: Profit per labor hour | B10: =IF(SUM('Job Tracker'!$E$5:$E$104)=0,0,B7/SUM('Job Tracker'!$E$5:$E$104))
A11: Jobs that lost money | B11: =COUNTIF('Job Tracker'!$J$5:$J$104,"<0")
A12: Jobs below target margin | B12: =COUNTIF('Job Tracker'!$K$5:$K$104,"<"&Settings!$B$6)
A13: Total profit vs plan | B13: =SUM('Job Tracker'!$M$5:$M$104)
A16: How to read it: if 'Profit vs plan' is negative, jobs are taking longer or costing more than you quoted. Raise the hours/price you use for that kind of job.

Sheet 12-Month Tracker
A1: 12-Month Tracker
A2: Enter the year and a monthly profit goal. Revenue, cost and profit fill in from the Job Tracker.
A3: Year | B3: 2026
A5: Month | B5: Revenue | C5: Actual cost | D5: Profit | E5: Margin | F5: Profit goal | G5: Over / under goal
A6: =DATE($B$3,1,1) | B6: =SUMIFS('Job Tracker'!$C$5:$C$104,'Job Tracker'!$A$5:$A$104,">="&$A6,'Job Tracker'!$A$5:$A$104,"<"&EDATE($A6,1)) | C6: =SUMIFS('Job Tracker'!$I$5:$I$104,'Job Tracker'!$A$5:$A$104,">="&$A6,'Job Tracker'!$A$5:$A$104,"<"&EDATE($A6,1)) | D6: =SUMIFS('Job Tracker'!$J$5:$J$104,'Job Tracker'!$A$5:$A$104,">="&$A6,'Job Tracker'!$A$5:$A$104,"<"&EDATE($A6,1)) | E6: =IF(B6=0,0,D6/B6) | G6: =IF(F6="","",D6-F6)
A7: =DATE($B$3,2,1) | B7: =SUMIFS('Job Tracker'!$C$5:$C$104,'Job Tracker'!$A$5:$A$104,">="&$A7,'Job Tracker'!$A$5:$A$104,"<"&EDATE($A7,1)) | C7: =SUMIFS('Job Tracker'!$I$5:$I$104,'Job Tracker'!$A$5:$A$104,">="&$A7,'Job Tracker'!$A$5:$A$104,"<"&EDATE($A7,1)) | D7: =SUMIFS('Job Tracker'!$J$5:$J$104,'Job Tracker'!$A$5:$A$104,">="&$A7,'Job Tracker'!$A$5:$A$104,"<"&EDATE($A7,1)) | E7: =IF(B7=0,0,D7/B7) | G7: =IF(F7="","",D7-F7)
A8: =DATE($B$3,3,1) | B8: =SUMIFS('Job Tracker'!$C$5:$C$104,'Job Tracker'!$A$5:$A$104,">="&$A8,'Job Tracker'!$A$5:$A$104,"<"&EDATE($A8,1)) | C8: =SUMIFS('Job Tracker'!$I$5:$I$104,'Job Tracker'!$A$5:$A$104,">="&$A8,'Job Tracker'!$A$5:$A$104,"<"&EDATE($A8,1)) | D8: =SUMIFS('Job Tracker'!$J$5:$J$104,'Job Tracker'!$A$5:$A$104,">="&$A8,'Job Tracker'!$A$5:$A$104,"<"&EDATE($A8,1)) | E8: =IF(B8=0,0,D8/B8) | G8: =IF(F8="","",D8-F8)
A9: =DATE($B$3,4,1) | B9: =SUMIFS('Job Tracker'!$C$5:$C$104,'Job Tracker'!$A$5:$A$104,">="&$A9,'Job Tracker'!$A$5:$A$104,"<"&EDATE($A9,1)) | C9: =SUMIFS('Job Tracker'!$I$5:$I$104,'Job Tracker'!$A$5:$A$104,">="&$A9,'Job Tracker'!$A$5:$A$104,"<"&EDATE($A9,1)) | D9: =SUMIFS('Job Tracker'!$J$5:$J$104,'Job Tracker'!$A$5:$A$104,">="&$A9,'Job Tracker'!$A$5:$A$104,"<"&EDATE($A9,1)) | E9: =IF(B9=0,0,D9/B9) | G9: =IF(F9="","",D9-F9)
A10: =DATE($B$3,5,1) | B10: =SUMIFS('Job Tracker'!$C$5:$C$104,'Job Tracker'!$A$5:$A$104,">="&$A10,'Job Tracker'!$A$5:$A$104,"<"&EDATE($A10,1)) | C10: =SUMIFS('Job Tracker'!$I$5:$I$104,'Job Tracker'!$A$5:$A$104,">="&$A10,'Job Tracker'!$A$5:$A$104,"<"&EDATE($A10,1)) | D10: =SUMIFS('Job Tracker'!$J$5:$J$104,'Job Tracker'!$A$5:$A$104,">="&$A10,'Job Tracker'!$A$5:$A$104,"<"&EDATE($A10,1)) | E10: =IF(B10=0,0,D10/B10) | G10: =IF(F10="","",D10-F10)
A11: =DATE($B$3,6,1) | B11: =SUMIFS('Job Tracker'!$C$5:$C$104,'Job Tracker'!$A$5:$A$104,">="&$A11,'Job Tracker'!$A$5:$A$104,"<"&EDATE($A11,1)) | C11: =SUMIFS('Job Tracker'!$I$5:$I$104,'Job Tracker'!$A$5:$A$104,">="&$A11,'Job Tracker'!$A$5:$A$104,"<"&EDATE($A11,1)) | D11: =SUMIFS('Job Tracker'!$J$5:$J$104,'Job Tracker'!$A$5:$A$104,">="&$A11,'Job Tracker'!$A$5:$A$104,"<"&EDATE($A11,1)) | E11: =IF(B11=0,0,D11/B11) | G11: =IF(F11="","",D11-F11)
A12: =DATE($B$3,7,1) | B12: =SUMIFS('Job Tracker'!$C$5:$C$104,'Job Tracker'!$A$5:$A$104,">="&$A12,'Job Tracker'!$A$5:$A$104,"<"&EDATE($A12,1)) | C12: =SUMIFS('Job Tracker'!$I$5:$I$104,'Job Tracker'!$A$5:$A$104,">="&$A12,'Job Tracker'!$A$5:$A$104,"<"&EDATE($A12,1)) | D12: =SUMIFS('Job Tracker'!$J$5:$J$104,'Job Tracker'!$A$5:$A$104,">="&$A12,'Job Tracker'!$A$5:$A$104,"<"&EDATE($A12,1)) | E12: =IF(B12=0,0,D12/B12) | G12: =IF(F12="","",D12-F12)
A13: =DATE($B$3,8,1) | B13: =SUMIFS('Job Tracker'!$C$5:$C$104,'Job Tracker'!$A$5:$A$104,">="&$A13,'Job Tracker'!$A$5:$A$104,"<"&EDATE($A13,1)) | C13: =SUMIFS('Job Tracker'!$I$5:$I$104,'Job Tracker'!$A$5:$A$104,">="&$A13,'Job Tracker'!$A$5:$A$104,"<"&EDATE($A13,1)) | D13: =SUMIFS('Job Tracker'!$J$5:$J$104,'Job Tracker'!$A$5:$A$104,">="&$A13,'Job Tracker'!$A$5:$A$104,"<"&EDATE($A13,1)) | E13: =IF(B13=0,0,D13/B13) | G13: =IF(F13="","",D13-F13)
A14: =DATE($B$3,9,1) | B14: =SUMIFS('Job Tracker'!$C$5:$C$104,'Job Tracker'!$A$5:$A$104,">="&$A14,'Job Tracker'!$A$5:$A$104,"<"&EDATE($A14,1)) | C14: =SUMIFS('Job Tracker'!$I$5:$I$104,'Job Tracker'!$A$5:$A$104,">="&$A14,'Job Tracker'!$A$5:$A$104,"<"&EDATE($A14,1)) | D14: =SUMIFS('Job Tracker'!$J$5:$J$104,'Job Tracker'!$A$5:$A$104,">="&$A14,'Job Tracker'!$A$5:$A$104,"<"&EDATE($A14,1)) | E14: =IF(B14=0,0,D14/B14) | G14: =IF(F14="","",D14-F14)
A15: =DATE($B$3,10,1) | B15: =SUMIFS('Job Tracker'!$C$5:$C$104,'Job Tracker'!$A$5:$A$104,">="&$A15,'Job Tracker'!$A$5:$A$104,"<"&EDATE($A15,1)) | C15: =SUMIFS('Job Tracker'!$I$5:$I$104,'Job Tracker'!$A$5:$A$104,">="&$A15,'Job Tracker'!$A$5:$A$104,"<"&EDATE($A15,1)) | D15: =SUMIFS('Job Tracker'!$J$5:$J$104,'Job Tracker'!$A$5:$A$104,">="&$A15,'Job Tracker'!$A$5:$A$104,"<"&EDATE($A15,1)) | E15: =IF(B15=0,0,D15/B15) | G15: =IF(F15="","",D15-F15)
A16: =DATE($B$3,11,1) | B16: =SUMIFS('Job Tracker'!$C$5:$C$104,'Job Tracker'!$A$5:$A$104,">="&$A16,'Job Tracker'!$A$5:$A$104,"<"&EDATE($A16,1)) | C16: =SUMIFS('Job Tracker'!$I$5:$I$104,'Job Tracker'!$A$5:$A$104,">="&$A16,'Job Tracker'!$A$5:$A$104,"<"&EDATE($A16,1)) | D16: =SUMIFS('Job Tracker'!$J$5:$J$104,'Job Tracker'!$A$5:$A$104,">="&$A16,'Job Tracker'!$A$5:$A$104,"<"&EDATE($A16,1)) | E16: =IF(B16=0,0,D16/B16) | G16: =IF(F16="","",D16-F16)
A17: =DATE($B$3,12,1) | B17: =SUMIFS('Job Tracker'!$C$5:$C$104,'Job Tracker'!$A$5:$A$104,">="&$A17,'Job Tracker'!$A$5:$A$104,"<"&EDATE($A17,1)) | C17: =SUMIFS('Job Tracker'!$I$5:$I$104,'Job Tracker'!$A$5:$A$104,">="&$A17,'Job Tracker'!$A$5:$A$104,"<"&EDATE($A17,1)) | D17: =SUMIFS('Job Tracker'!$J$5:$J$104,'Job Tracker'!$A$5:$A$104,">="&$A17,'Job Tracker'!$A$5:$A$104,"<"&EDATE($A17,1)) | E17: =IF(B17=0,0,D17/B17) | G17: =IF(F17="","",D17-F17)
A18: YEAR TOTAL | B18: =SUM(B6:B17) | C18: =SUM(C6:C17) | D18: =SUM(D6:D17) | E18: =IF(B18=0,0,D18/B18) | F18: =SUM(F6:F17) | G18: =D18-F18

Sheet Client Tracker
A1: Client Tracker
A2: One row per client. Sort or filter by any column.
A4: Client name | B4: Phone | C4: Email | D4: Address / area | E4: Service type | F4: Frequency | G4: Price per visit | H4: Start date | I4: Last service | J4: Next follow-up | K4: Status | L4: Notes

Sheet Follow-Up Templates
A1: Follow-Up Message Templates
A2: Copy, replace the [brackets], send. Get consent before texting or emailing marketing messages and honor opt-outs.
A4: When to use | B4: Message
A5: Quote follow-up (2 days after sending a quote) | B5: Hi [Client Name], this is [Your Name] from [Business]. I sent your cleaning quote for [Service] on [Day]. Do you have any questions, or would you like me to hold a time for you on [Date]? Happy to adjust the scope if that helps.
A6: Quote follow-up (7 days, last touch) | B6: Hi [Client Name], I'm closing out quotes from last week and didn't want to lose touch. If you're still interested, I can fit you in on [Date]. If now isn't the right time, no problem at all - just let me know.
A7: After the first clean | B7: Hi [Client Name], thanks for having us today! Was everything how you wanted it? If anything was missed, tell me and we'll make it right. If you'd like us to come back on a regular schedule, I can set up [Frequency] visits at [Price].
A8: Recurring offer | B8: Hi [Client Name], since we've cleaned for you once, I can offer a recurring rate of [Price] per visit for [Frequency] service. Want me to put you on the calendar starting [Date]?
A9: Asking for a review | B9: Hi [Client Name], thank you for choosing [Business]. If you were happy with the clean, an honest review at [Review Link] helps a small business like ours. Whatever your experience was, we'd value your feedback.
A10: Lapsed client check-in (60+ days) | B10: Hi [Client Name], it's been a while since your last clean. Would you like to schedule one for [Date]? I have openings on [Days].
A11: Price update notice (give 30 days' notice) | B11: Hi [Client Name], to keep our quality and our team paid fairly, our price for your [Service] will change from [Old Price] to [New Price] starting [Date]. Thank you for being a valued client; call me with any questions.
A12: Reschedule / cancellation reply | B12: Hi [Client Name], no problem - I can move your clean to [Date/Time]. Per our policy, cancellations within [24] hours of the visit may carry a fee of [Amount]. Which time works best?
