Workbook

Sheet Start Here
A1: Cleaning Business Job Profit & Quote Calculator
A2: Start here
A4: What this does | B4: Tells you what to charge so a job actually makes the profit you want, then shows whether the job did.
A5: Step 1 | B5: Go to the Settings sheet. Enter your labor cost per hour, overhead %, target margin, mileage cost, recurring discount and minimum price.
A6: Step 2 | B6: Go to the Quote sheet. Describe the job in the yellow cells. Quote the price in 'QUOTE THIS PRICE'.
A7: Step 3 | B7: See the Examples sheet for three fictional jobs (a recurring home, a move-out deep clean, a small office).
A8: Colors | B8: Yellow = you type here. Gray = calculated, don't type over it. Blue = key results.
A9: Margin vs markup | B9: Margin = profit / price. Markup = profit / cost. Example: a job costs $100. A 40% margin means price = 100 / (1 - 0.40) = $166.67, profit $66.67. That is a 66.7% markup but a 40% margin. This sheet uses margin so your profit % is what you really keep.
A10: Google Sheets | B10: Upload this file to Google Drive and open with Google Sheets, or use File > Import. All formulas are standard and work in both.
A11: Not included | B11: No macros. No tax, payroll or accounting features. This workbook is a planning tool. It is not tax, accounting, legal or financial advice. Check your numbers with your own accountant.
A12: Support | B12: This is a template. It can't know your costs. If a result looks wrong, check your Settings first.

Sheet Settings
A1: Settings
A2: Starter values are filled in so the Examples work. REPLACE them with your own numbers.
A3: Setting | B3: Value | C3: What it means
A4: Labor cost per cleaner-hour | B4: 18 | C4: What one cleaner costs you per hour: wages PLUS payroll taxes/workers' comp. Pay yourself too.
A5: Overhead (% added on top of direct cost) | B5: 0.1 | C5: Insurance, software, phone, cleaning equipment wear, admin time. 8-15% is common; use your real number.
A6: Target profit margin | B6: 0.35 | C6: Profit as a % of the PRICE (not of cost). 35% margin means $35 of every $100 you charge is profit.
A7: Vehicle cost per mile | B7: 0.67 | C7: Your real cost to drive one mile (fuel, wear, insurance). Check the current IRS mileage rate as a reference.
A8: Recurring-client discount | B8: 0.1 | C8: Discount off the one-time price for recurring clients. Enter 0% for none.
A9: Minimum job price | B9: 90 | C9: Never quote below this, even for a tiny job.
A11: This workbook is a planning tool. It is not tax, accounting, legal or financial advice. Check your numbers with your own accountant.

Sheet Quote
A1: Job Quote Calculator
A2: Fill the yellow cells. Gray cells calculate. Quote the 'QUOTE THIS PRICE' number.
A3: Client / job name | B3: Standard 3BR/2BA - biweekly
A4: Job type (One-time or Recurring) | B4: Recurring
A5: Number of cleaners | B5: 2
A6: Hours on site per cleaner | B6: 2
A7: Supplies & materials for this visit ($) | B7: 6
A8: Round-trip miles (all vehicles) | B8: 14
A9: Other direct costs ($, e.g. equipment rental) | B9: 0
A10: Visits per month (recurring jobs only) | B10: 2
A12: RESULTS
A13: Total labor hours | B13: =B5*B6
A14: Labor cost | B14: =B13*Settings!$B$4
A15: Travel cost | B15: =B8*Settings!$B$7
A16: Direct cost (labor + travel + supplies + other) | B16: =B14+B15+B7+B9
A17: Overhead | B17: =B16*Settings!$B$5
A18: TOTAL COST to do this visit | B18: =B16+B17
A19: Price needed to hit your target margin | B19: =IF(Settings!$B$6>=1,0,B18/(1-Settings!$B$6))
A20: Recurring discount applied | B20: =IF(B4="Recurring",B19*Settings!$B$8,0)
A21: QUOTE THIS PRICE (per visit) | B21: =MAX(Settings!$B$9,ROUNDUP(B19-B20,0)) | C21: Rounded up to the next whole dollar and never below your minimum job price.
A22: Profit per visit | B22: =B21-B18
A23: Profit margin (profit / price) | B23: =IF(B21=0,0,B22/B21) | C23: Margin = profit / PRICE. This is what you keep from every dollar charged.
A24: Markup on cost (profit / cost) | B24: =IF(B18=0,0,B22/B18) | C24: Markup = profit / COST. A 50% markup is only a 33% margin. Don't mix them up.
A25: Profit per labor hour | B25: =IF(B13=0,0,B22/B13) | C25: Profit left after ALL costs, divided by labor hours.
A26: Monthly revenue (recurring) | B26: =IF(B4="Recurring",B21*B10,0)
A27: Monthly profit (recurring) | B27: =IF(B4="Recurring",B22*B10,0)
A28: Check | B28: =IF(Settings!$B$6>=1,"Fix target margin on Settings (must be under 100%)",IF(B13=0,"Enter cleaners and hours to get a result",IF(B22<0,"LOSING MONEY - raise the price",IF(B23<Settings!$B$6-0.0001,"Below target margin because of the recurring discount - fine if intended","OK - at or above target margin"))))
A30: This workbook is a planning tool. It is not tax, accounting, legal or financial advice. Check your numbers with your own accountant.

Sheet Examples
A1: Three example jobs (fictional)
A2: Same math as the Quote sheet, using your Settings. Change Settings to see prices move.
A3: Client / job name | B3: Standard 3BR/2BA - biweekly | C3: Move-out deep clean - 4BR | D3: Small office - nightly, 5x/week
A4: Job type (One-time or Recurring) | B4: Recurring | C4: One-time | D4: Recurring
A5: Number of cleaners | B5: 2 | C5: 3 | D5: 1
A6: Hours on site per cleaner | B6: 2 | C6: 3 | D6: 1.5
A7: Supplies & materials for this visit ($) | B7: 6 | C7: 25 | D7: 5
A8: Round-trip miles (all vehicles) | B8: 14 | C8: 22 | D8: 8
A9: Other direct costs ($, e.g. equipment rental) | B9: 0 | C9: 15 | D9: 0
A10: Visits per month (recurring jobs only) | B10: 2 | D10: 22
A12: RESULTS
A13: Total labor hours | B13: =B5*B6 | C13: =C5*C6 | D13: =D5*D6
A14: Labor cost | B14: =B13*Settings!$B$4 | C14: =C13*Settings!$B$4 | D14: =D13*Settings!$B$4
A15: Travel cost | B15: =B8*Settings!$B$7 | C15: =C8*Settings!$B$7 | D15: =D8*Settings!$B$7
A16: Direct cost (labor + travel + supplies + other) | B16: =B14+B15+B7+B9 | C16: =C14+C15+C7+C9 | D16: =D14+D15+D7+D9
A17: Overhead | B17: =B16*Settings!$B$5 | C17: =C16*Settings!$B$5 | D17: =D16*Settings!$B$5
A18: TOTAL COST to do this visit | B18: =B16+B17 | C18: =C16+C17 | D18: =D16+D17
A19: Price needed to hit your target margin | B19: =IF(Settings!$B$6>=1,0,B18/(1-Settings!$B$6)) | C19: =IF(Settings!$B$6>=1,0,C18/(1-Settings!$B$6)) | D19: =IF(Settings!$B$6>=1,0,D18/(1-Settings!$B$6))
A20: Recurring discount applied | B20: =IF(B4="Recurring",B19*Settings!$B$8,0) | C20: =IF(C4="Recurring",C19*Settings!$B$8,0) | D20: =IF(D4="Recurring",D19*Settings!$B$8,0)
A21: QUOTE THIS PRICE (per visit) | B21: =MAX(Settings!$B$9,ROUNDUP(B19-B20,0)) | C21: =MAX(Settings!$B$9,ROUNDUP(C19-C20,0)) | D21: =MAX(Settings!$B$9,ROUNDUP(D19-D20,0))
A22: Profit per visit | B22: =B21-B18 | C22: =C21-C18 | D22: =D21-D18
A23: Profit margin (profit / price) | B23: =IF(B21=0,0,B22/B21) | C23: =IF(C21=0,0,C22/C21) | D23: =IF(D21=0,0,D22/D21)
A24: Markup on cost (profit / cost) | B24: =IF(B18=0,0,B22/B18) | C24: =IF(C18=0,0,C22/C18) | D24: =IF(D18=0,0,D22/D18)
A25: Profit per labor hour | B25: =IF(B13=0,0,B22/B13) | C25: =IF(C13=0,0,C22/C13) | D25: =IF(D13=0,0,D22/D13)
A26: Monthly revenue (recurring) | B26: =IF(B4="Recurring",B21*B10,0) | C26: =IF(C4="Recurring",C21*C10,0) | D26: =IF(D4="Recurring",D21*D10,0)
A27: Monthly profit (recurring) | B27: =IF(B4="Recurring",B22*B10,0) | C27: =IF(C4="Recurring",C22*C10,0) | D27: =IF(D4="Recurring",D22*D10,0)
A28: Check | B28: =IF(Settings!$B$6>=1,"Fix target margin on Settings (must be under 100%)",IF(B13=0,"Enter cleaners and hours to get a result",IF(B22<0,"LOSING MONEY - raise the price",IF(B23<Settings!$B$6-0.0001,"Below target margin because of the recurring discount - fine if intended","OK - at or above target margin")))) | C28: =IF(Settings!$B$6>=1,"Fix target margin on Settings (must be under 100%)",IF(C13=0,"Enter cleaners and hours to get a result",IF(C22<0,"LOSING MONEY - raise the price",IF(C23<Settings!$B$6-0.0001,"Below target margin because of the recurring discount - fine if intended","OK - at or above target margin")))) | D28: =IF(Settings!$B$6>=1,"Fix target margin on Settings (must be under 100%)",IF(D13=0,"Enter cleaners and hours to get a result",IF(D22<0,"LOSING MONEY - raise the price",IF(D23<Settings!$B$6-0.0001,"Below target margin because of the recurring discount - fine if intended","OK - at or above target margin"))))
