Workbook

Sheet Goal
A1: Rent goal
A3: Amount needed NET (after fees), on top of other income | B3: 2000
A4: Platform fee % (Fiverr reported 20%; check each platform) | B4: 0.2
A5: Gross sales needed | B5: =IF(B4>=1,0,B3/(1-B4))
A6: Net cash RECEIVED so far (payouts that have cleared) | B6: =SUMIFS(Orders!$K:$K,Orders!$L:$L,"yes")
A7: Net still pending clearance | B7: =SUMIFS(Orders!$K:$K,Orders!$L:$L,"<>yes")
A8: Remaining to reach goal (cleared only) | B8: =MAX(0,B3-B6)
A9: Goal date | B9: 46327
A10: Days left | B10: =MAX(0,B9-TODAY())
A12: Cash only counts when the payout has cleared. Mark the 'Cleared?' column on the Orders sheet.

Sheet Orders
A1: Date ordered | B1: Offer | C1: Platform | D1: Customer / order # | E1: Gross price | F1: Fee % | G1: Fee $ | H1: Hours spent | I1: Delivered on | J1: Cleared on | K1: Net received | L1: Cleared? | M1: Refunded $ | N1: Net $/hour | O1: Notes
F2: =IF(E2="","",Goal!$B$4) | G2: =IF(E2="","",E2*F2) | K2: =IF(E2="","",E2-G2-N(M2)) | N2: =IF(OR(E2="",H2="",H2=0),"",K2/H2)
F3: =IF(E3="","",Goal!$B$4) | G3: =IF(E3="","",E3*F3) | K3: =IF(E3="","",E3-G3-N(M3)) | N3: =IF(OR(E3="",H3="",H3=0),"",K3/H3)
F4: =IF(E4="","",Goal!$B$4) | G4: =IF(E4="","",E4*F4) | K4: =IF(E4="","",E4-G4-N(M4)) | N4: =IF(OR(E4="",H4="",H4=0),"",K4/H4)
F5: =IF(E5="","",Goal!$B$4) | G5: =IF(E5="","",E5*F5) | K5: =IF(E5="","",E5-G5-N(M5)) | N5: =IF(OR(E5="",H5="",H5=0),"",K5/H5)
F6: =IF(E6="","",Goal!$B$4) | G6: =IF(E6="","",E6*F6) | K6: =IF(E6="","",E6-G6-N(M6)) | N6: =IF(OR(E6="",H6="",H6=0),"",K6/H6)
F7: =IF(E7="","",Goal!$B$4) | G7: =IF(E7="","",E7*F7) | K7: =IF(E7="","",E7-G7-N(M7)) | N7: =IF(OR(E7="",H7="",H7=0),"",K7/H7)
F8: =IF(E8="","",Goal!$B$4) | G8: =IF(E8="","",E8*F8) | K8: =IF(E8="","",E8-G8-N(M8)) | N8: =IF(OR(E8="",H8="",H8=0),"",K8/H8)
F9: =IF(E9="","",Goal!$B$4) | G9: =IF(E9="","",E9*F9) | K9: =IF(E9="","",E9-G9-N(M9)) | N9: =IF(OR(E9="",H9="",H9=0),"",K9/H9)
F10: =IF(E10="","",Goal!$B$4) | G10: =IF(E10="","",E10*F10) | K10: =IF(E10="","",E10-G10-N(M10)) | N10: =IF(OR(E10="",H10="",H10=0),"",K10/H10)
F11: =IF(E11="","",Goal!$B$4) | G11: =IF(E11="","",E11*F11) | K11: =IF(E11="","",E11-G11-N(M11)) | N11: =IF(OR(E11="",H11="",H11=0),"",K11/H11)
F12: =IF(E12="","",Goal!$B$4) | G12: =IF(E12="","",E12*F12) | K12: =IF(E12="","",E12-G12-N(M12)) | N12: =IF(OR(E12="",H12="",H12=0),"",K12/H12)
F13: =IF(E13="","",Goal!$B$4) | G13: =IF(E13="","",E13*F13) | K13: =IF(E13="","",E13-G13-N(M13)) | N13: =IF(OR(E13="",H13="",H13=0),"",K13/H13)
... F301: =IF(E301="","",Goal!$B$4) | G301: =IF(E301="","",E301*F301) | K301: =IF(E301="","",E301-G301-N(M301)) | N301: =IF(OR(E301="",H301="",H301=0),"",K301/H301)

Sheet Daily Metrics
A1: Date | B1: Offer | C1: Impressions | D1: Clicks | E1: Inquiries | F1: Orders | G1: Click rate | H1: Inquiry rate | I1: Order rate | J1: Notes / change made
A2: 46305 | B2: Fiverr: n8n/Make/Zapier fix | G2: =IF(N(C2)=0,"",D2/C2) | H2: =IF(N(D2)=0,"",E2/D2) | I2: =IF(N(E2)=0,"",F2/E2)
A3: 46305 | B3: Fiverr: Claude Code debugging | G3: =IF(N(C3)=0,"",D3/C3) | H3: =IF(N(D3)=0,"",E3/D3) | I3: =IF(N(E3)=0,"",F3/E3)
A4: 46305 | B4: Fiverr: Stripe fix | G4: =IF(N(C4)=0,"",D4/C4) | H4: =IF(N(D4)=0,"",E4/D4) | I4: =IF(N(E4)=0,"",F4/E4)
A5: 46305 | B5: Fiverr: Excel/CSV cleaning | G5: =IF(N(C5)=0,"",D5/C5) | H5: =IF(N(D5)=0,"",E5/D5) | I5: =IF(N(E5)=0,"",F5/E5)
A6: 46305 | B6: Cleaning Quote Calculator | G6: =IF(N(C6)=0,"",D6/C6) | H6: =IF(N(D6)=0,"",E6/D6) | I6: =IF(N(E6)=0,"",F6/E6)
A7: 46305 | B7: n8n pack: Agency Onboarding | G7: =IF(N(C7)=0,"",D7/C7) | H7: =IF(N(D7)=0,"",E7/D7) | I7: =IF(N(E7)=0,"",F7/E7)
A8: 46305 | B8: n8n pack: Cleaning Lead-to-Booking | G8: =IF(N(C8)=0,"",D8/C8) | H8: =IF(N(D8)=0,"",E8/D8) | I8: =IF(N(E8)=0,"",F8/E8)
A9: 46305 | B9: Other | G9: =IF(N(C9)=0,"",D9/C9) | H9: =IF(N(D9)=0,"",E9/D9) | I9: =IF(N(E9)=0,"",F9/E9)
A10: 46306 | B10: Fiverr: n8n/Make/Zapier fix | G10: =IF(N(C10)=0,"",D10/C10) | H10: =IF(N(D10)=0,"",E10/D10) | I10: =IF(N(E10)=0,"",F10/E10)
A11: 46306 | B11: Fiverr: Claude Code debugging | G11: =IF(N(C11)=0,"",D11/C11) | H11: =IF(N(D11)=0,"",E11/D11) | I11: =IF(N(E11)=0,"",F11/E11)
A12: 46306 | B12: Fiverr: Stripe fix | G12: =IF(N(C12)=0,"",D12/C12) | H12: =IF(N(D12)=0,"",E12/D12) | I12: =IF(N(E12)=0,"",F12/E12)
A13: 46306 | B13: Fiverr: Excel/CSV cleaning | G13: =IF(N(C13)=0,"",D13/C13) | H13: =IF(N(D13)=0,"",E13/D13) | I13: =IF(N(E13)=0,"",F13/E13)
... A113: 46318 | B113: Other | G113: =IF(N(C113)=0,"",D113/C113) | H113: =IF(N(D113)=0,"",E113/D113) | I113: =IF(N(E113)=0,"",F113/E113)

Sheet By Offer
A1: Offer | B1: Impressions | C1: Clicks | D1: Inquiries | E1: Orders (logged) | F1: Gross sales | G1: Net received | H1: Hours | I1: Net $/hour | J1: Verdict
A2: Fiverr: n8n/Make/Zapier fix | B2: =SUMIFS('Daily Metrics'!$C:$C,'Daily Metrics'!$B:$B,$A2) | C2: =SUMIFS('Daily Metrics'!$D:$D,'Daily Metrics'!$B:$B,$A2) | D2: =SUMIFS('Daily Metrics'!$E:$E,'Daily Metrics'!$B:$B,$A2) | E2: =COUNTIFS(Orders!$B:$B,$A2,Orders!$E:$E,">0") | F2: =SUMIFS(Orders!$E:$E,Orders!$B:$B,$A2) | G2: =SUMIFS(Orders!$K:$K,Orders!$B:$B,$A2) | H2: =SUMIFS(Orders!$H:$H,Orders!$B:$B,$A2) | I2: =IF(H2=0,"",G2/H2) | J2: =IF(B2<100,"Too early (under 100 impressions)",IF(C2/B2<0.01,"Fix title/thumbnail (low clicks)",IF(D2=0,"Fix demo/price (clicks, no inquiries)",IF(E2=0,"Fix offer/response (inquiries, no orders)","Working - double down"))))
A3: Fiverr: Claude Code debugging | B3: =SUMIFS('Daily Metrics'!$C:$C,'Daily Metrics'!$B:$B,$A3) | C3: =SUMIFS('Daily Metrics'!$D:$D,'Daily Metrics'!$B:$B,$A3) | D3: =SUMIFS('Daily Metrics'!$E:$E,'Daily Metrics'!$B:$B,$A3) | E3: =COUNTIFS(Orders!$B:$B,$A3,Orders!$E:$E,">0") | F3: =SUMIFS(Orders!$E:$E,Orders!$B:$B,$A3) | G3: =SUMIFS(Orders!$K:$K,Orders!$B:$B,$A3) | H3: =SUMIFS(Orders!$H:$H,Orders!$B:$B,$A3) | I3: =IF(H3=0,"",G3/H3) | J3: =IF(B3<100,"Too early (under 100 impressions)",IF(C3/B3<0.01,"Fix title/thumbnail (low clicks)",IF(D3=0,"Fix demo/price (clicks, no inquiries)",IF(E3=0,"Fix offer/response (inquiries, no orders)","Working - double down"))))
A4: Fiverr: Stripe fix | B4: =SUMIFS('Daily Metrics'!$C:$C,'Daily Metrics'!$B:$B,$A4) | C4: =SUMIFS('Daily Metrics'!$D:$D,'Daily Metrics'!$B:$B,$A4) | D4: =SUMIFS('Daily Metrics'!$E:$E,'Daily Metrics'!$B:$B,$A4) | E4: =COUNTIFS(Orders!$B:$B,$A4,Orders!$E:$E,">0") | F4: =SUMIFS(Orders!$E:$E,Orders!$B:$B,$A4) | G4: =SUMIFS(Orders!$K:$K,Orders!$B:$B,$A4) | H4: =SUMIFS(Orders!$H:$H,Orders!$B:$B,$A4) | I4: =IF(H4=0,"",G4/H4) | J4: =IF(B4<100,"Too early (under 100 impressions)",IF(C4/B4<0.01,"Fix title/thumbnail (low clicks)",IF(D4=0,"Fix demo/price (clicks, no inquiries)",IF(E4=0,"Fix offer/response (inquiries, no orders)","Working - double down"))))
A5: Fiverr: Excel/CSV cleaning | B5: =SUMIFS('Daily Metrics'!$C:$C,'Daily Metrics'!$B:$B,$A5) | C5: =SUMIFS('Daily Metrics'!$D:$D,'Daily Metrics'!$B:$B,$A5) | D5: =SUMIFS('Daily Metrics'!$E:$E,'Daily Metrics'!$B:$B,$A5) | E5: =COUNTIFS(Orders!$B:$B,$A5,Orders!$E:$E,">0") | F5: =SUMIFS(Orders!$E:$E,Orders!$B:$B,$A5) | G5: =SUMIFS(Orders!$K:$K,Orders!$B:$B,$A5) | H5: =SUMIFS(Orders!$H:$H,Orders!$B:$B,$A5) | I5: =IF(H5=0,"",G5/H5) | J5: =IF(B5<100,"Too early (under 100 impressions)",IF(C5/B5<0.01,"Fix title/thumbnail (low clicks)",IF(D5=0,"Fix demo/price (clicks, no inquiries)",IF(E5=0,"Fix offer/response (inquiries, no orders)","Working - double down"))))
A6: Cleaning Quote Calculator | B6: =SUMIFS('Daily Metrics'!$C:$C,'Daily Metrics'!$B:$B,$A6) | C6: =SUMIFS('Daily Metrics'!$D:$D,'Daily Metrics'!$B:$B,$A6) | D6: =SUMIFS('Daily Metrics'!$E:$E,'Daily Metrics'!$B:$B,$A6) | E6: =COUNTIFS(Orders!$B:$B,$A6,Orders!$E:$E,">0") | F6: =SUMIFS(Orders!$E:$E,Orders!$B:$B,$A6) | G6: =SUMIFS(Orders!$K:$K,Orders!$B:$B,$A6) | H6: =SUMIFS(Orders!$H:$H,Orders!$B:$B,$A6) | I6: =IF(H6=0,"",G6/H6) | J6: =IF(B6<100,"Too early (under 100 impressions)",IF(C6/B6<0.01,"Fix title/thumbnail (low clicks)",IF(D6=0,"Fix demo/price (clicks, no inquiries)",IF(E6=0,"Fix offer/response (inquiries, no orders)","Working - double down"))))
A7: n8n pack: Agency Onboarding | B7: =SUMIFS('Daily Metrics'!$C:$C,'Daily Metrics'!$B:$B,$A7) | C7: =SUMIFS('Daily Metrics'!$D:$D,'Daily Metrics'!$B:$B,$A7) | D7: =SUMIFS('Daily Metrics'!$E:$E,'Daily Metrics'!$B:$B,$A7) | E7: =COUNTIFS(Orders!$B:$B,$A7,Orders!$E:$E,">0") | F7: =SUMIFS(Orders!$E:$E,Orders!$B:$B,$A7) | G7: =SUMIFS(Orders!$K:$K,Orders!$B:$B,$A7) | H7: =SUMIFS(Orders!$H:$H,Orders!$B:$B,$A7) | I7: =IF(H7=0,"",G7/H7) | J7: =IF(B7<100,"Too early (under 100 impressions)",IF(C7/B7<0.01,"Fix title/thumbnail (low clicks)",IF(D7=0,"Fix demo/price (clicks, no inquiries)",IF(E7=0,"Fix offer/response (inquiries, no orders)","Working - double down"))))
A8: n8n pack: Cleaning Lead-to-Booking | B8: =SUMIFS('Daily Metrics'!$C:$C,'Daily Metrics'!$B:$B,$A8) | C8: =SUMIFS('Daily Metrics'!$D:$D,'Daily Metrics'!$B:$B,$A8) | D8: =SUMIFS('Daily Metrics'!$E:$E,'Daily Metrics'!$B:$B,$A8) | E8: =COUNTIFS(Orders!$B:$B,$A8,Orders!$E:$E,">0") | F8: =SUMIFS(Orders!$E:$E,Orders!$B:$B,$A8) | G8: =SUMIFS(Orders!$K:$K,Orders!$B:$B,$A8) | H8: =SUMIFS(Orders!$H:$H,Orders!$B:$B,$A8) | I8: =IF(H8=0,"",G8/H8) | J8: =IF(B8<100,"Too early (under 100 impressions)",IF(C8/B8<0.01,"Fix title/thumbnail (low clicks)",IF(D8=0,"Fix demo/price (clicks, no inquiries)",IF(E8=0,"Fix offer/response (inquiries, no orders)","Working - double down"))))
A9: Other | B9: =SUMIFS('Daily Metrics'!$C:$C,'Daily Metrics'!$B:$B,$A9) | C9: =SUMIFS('Daily Metrics'!$D:$D,'Daily Metrics'!$B:$B,$A9) | D9: =SUMIFS('Daily Metrics'!$E:$E,'Daily Metrics'!$B:$B,$A9) | E9: =COUNTIFS(Orders!$B:$B,$A9,Orders!$E:$E,">0") | F9: =SUMIFS(Orders!$E:$E,Orders!$B:$B,$A9) | G9: =SUMIFS(Orders!$K:$K,Orders!$B:$B,$A9) | H9: =SUMIFS(Orders!$H:$H,Orders!$B:$B,$A9) | I9: =IF(H9=0,"",G9/H9) | J9: =IF(B9<100,"Too early (under 100 impressions)",IF(C9/B9<0.01,"Fix title/thumbnail (low clicks)",IF(D9=0,"Fix demo/price (clicks, no inquiries)",IF(E9=0,"Fix offer/response (inquiries, no orders)","Working - double down"))))
A10: TOTAL | B10: =SUM(B2:B9) | C10: =SUM(C2:C9) | D10: =SUM(D2:D9) | E10: =SUM(E2:E9) | F10: =SUM(F2:F9) | G10: =SUM(G2:G9) | H10: =SUM(H2:H9)

Sheet Lists
A1: Offers
A2: Fiverr: n8n/Make/Zapier fix
A3: Fiverr: Claude Code debugging
A4: Fiverr: Stripe fix
A5: Fiverr: Excel/CSV cleaning
A6: Cleaning Quote Calculator
A7: n8n pack: Agency Onboarding
A8: n8n pack: Cleaning Lead-to-Booking
A9: Other
